growatt_client/__init__.py
growatt_client/const.py
growatt_client/growatt.py
growatt_client-1.0.6.dist-info/LICENSE
growatt_client-1.0.6.dist-info/METADATA
growatt_client-1.0.6.dist-info/WHEEL
growatt_client-1.0.6.dist-info/top_level.txt
growatt_client-1.0.6.dist-info/RECORD
