Metadata-Version: 2.1
Name: growatt-client
Version: 1.0.6
Summary: Python wrapper for getting data asynchronously
Home-page: https://github.com/henols/growatt-client
Author: Henrik Olsson
Author-email: henols@gmail.com
Project-URL: Bug Tracker, https://github.com/henols/growatt-client/issues
Project-URL: Source, https://github.com/henols/growatt-client
Classifier: Programming Language :: Python :: 3
Classifier: License :: OSI Approved :: MIT License
Classifier: Operating System :: OS Independent
Requires-Python: >=3.6
License-File: LICENSE
Requires-Dist: pymodbus (==3.1.2)
